pytom_match_pick-0.12.1.dist-info/licenses/LICENSE
pytom_tm/__init__.py
pytom_tm/angles.py
pytom_tm/correlation.py
pytom_tm/dataclass.py
pytom_tm/entry_points.py
pytom_tm/extract.py
pytom_tm/io.py
pytom_tm/json.py
pytom_tm/mask.py
pytom_tm/matching.py
pytom_tm/merge_stars.py
pytom_tm/parallel.py
pytom_tm/plotting.py
pytom_tm/template.py
pytom_tm/tmjob.py
pytom_tm/utils.py
pytom_tm/weights.py
pytom_match_pick-0.12.1.dist-info/METADATA
pytom_match_pick-0.12.1.dist-info/WHEEL
pytom_match_pick-0.12.1.dist-info/entry_points.txt
pytom_match_pick-0.12.1.dist-info/top_level.txt
pytom_match_pick-0.12.1.dist-info/RECORD
