Metadata-Version: 2.4
Name: pytom-match-pick
Version: 0.12.1
Summary: PyTOM's GPU template matching module as an independent package
Author-email: Marten Chaillet <m.l.chaillet@uu.nl>, Sander Roet <s.j.s.roet@uu.nl>
License:                     GNU GENERAL PUBLIC LICENSE
Project-URL: Repository, https://github.com/SBC-Utrecht/pytom-match-pick
Project-URL: Issues, https://github.com/SBC-Utrecht/pytom-match-pick/issues
Classifier: Development Status :: 4 - Beta
Classifier: Environment :: GPU :: NVIDIA CUDA
Classifier: License :: OSI Approved :: GNU General Public License v2 (GPLv2)
Classifier: Intended Audience :: Science/Research
Classifier: Natural Language :: English
Classifier: Operating System :: OS Independent
Classifier: Programming Language :: Python :: 3 :: Only
Classifier: Topic :: Scientific/Engineering
Classifier: Typing :: Typed
Requires-Python: >=3.11
License-File: LICENSE
Requires-Dist: numpy
Requires-Dist: cupy!=13.0.*
Requires-Dist: voltools
Requires-Dist: tqdm
Requires-Dist: mrcfile
Requires-Dist: starfile
Requires-Dist: importlib_resources
Requires-Dist: packaging
Requires-Dist: scipy
Requires-Dist: healpix
Requires-Dist: lxml
Provides-Extra: plotting
Requires-Dist: matplotlib; extra == "plotting"
Requires-Dist: seaborn; extra == "plotting"
Provides-Extra: dev
Requires-Dist: ruff; extra == "dev"
Requires-Dist: pre-commit; extra == "dev"
Requires-Dist: mkdocs; extra == "dev"
Requires-Dist: mkdocs-material; extra == "dev"
Requires-Dist: markdown-exec; extra == "dev"
Requires-Dist: mkdocs-glightbox; extra == "dev"
Provides-Extra: all
Requires-Dist: pytom-match-pick[plotting]; extra == "all"
Requires-Dist: pytom-match-pick[dev]; extra == "all"
Dynamic: license-file
